disk_cached/__init__.py
disk_cached/cache_manager.py
disk_cached-0.1.0.dist-info/LICENSE
disk_cached-0.1.0.dist-info/METADATA
disk_cached-0.1.0.dist-info/WHEEL
disk_cached-0.1.0.dist-info/top_level.txt
disk_cached-0.1.0.dist-info/RECORD
