Metadata-Version: 2.2
Name: disk_cached
Version: 0.1.0
Summary: A simple module for caching with diskcache.
Home-page: https://github.com/tu_usuario/mi_modulo
Author: David Lorenzana
Author-email: tu_email@example.com
License: MIT
Classifier: Programming Language :: Python :: 3
Classifier: License :: OSI Approved :: MIT License
Classifier: Operating System :: OS Independent
Requires-Python: >=3.7
License-File: LICENSE
Requires-Dist: diskcache>=5.6.1
Dynamic: author
Dynamic: author-email
Dynamic: classifier
Dynamic: description-content-type
Dynamic: home-page
Dynamic: license
Dynamic: requires-dist
Dynamic: requires-python
Dynamic: summary
